Metadata-Version: 2.1
Name: replicate-api-utils
Version: 0.1.5
Summary: Python package for accessing the Replicate API
Author: Julian Otto
Author-email: julianotto@outlook.com
